tests_store/__init__.py
tests_store/test___init__.py
tests_store/test_permission.py
tests_store/base/__init__.py
tests_store/base/unittest_base.py
tests_store/resources/__init__.py
tests_store/resources/test_algorithm.py
tests_store/resources/test_policy.py
tests_store/resources/test_review.py
tests_store/resources/test_role.py
tests_store/resources/test_rule.py
tests_store/resources/test_user.py
tests_store/resources/test_v6server.py
tests_store/resources/test_version.py
vantage6/algorithm/store/__build__
vantage6/algorithm/store/__init__.py
vantage6/algorithm/store/_version.py
vantage6/algorithm/store/db.py
vantage6/algorithm/store/default_roles.py
vantage6/algorithm/store/globals.py
vantage6/algorithm/store/permission.py
vantage6/algorithm/store/wsgi.py
vantage6/algorithm/store/model/__init__.py
vantage6/algorithm/store/model/algorithm.py
vantage6/algorithm/store/model/allowed_argument_value.py
vantage6/algorithm/store/model/argument.py
vantage6/algorithm/store/model/base.py
vantage6/algorithm/store/model/database.py
vantage6/algorithm/store/model/function.py
vantage6/algorithm/store/model/permission.py
vantage6/algorithm/store/model/policy.py
vantage6/algorithm/store/model/review.py
vantage6/algorithm/store/model/role.py
vantage6/algorithm/store/model/role_rule_association.py
vantage6/algorithm/store/model/rule.py
vantage6/algorithm/store/model/ui_visualization.py
vantage6/algorithm/store/model/user.py
vantage6/algorithm/store/model/vantage6_server.py
vantage6/algorithm/store/model/common/enums.py
vantage6/algorithm/store/model/common/ui_visualization_schemas.py
vantage6/algorithm/store/resource/__init__.py
vantage6/algorithm/store/resource/algorithm.py
vantage6/algorithm/store/resource/policy.py
vantage6/algorithm/store/resource/review.py
vantage6/algorithm/store/resource/role.py
vantage6/algorithm/store/resource/rule.py
vantage6/algorithm/store/resource/user.py
vantage6/algorithm/store/resource/vantage6_server.py
vantage6/algorithm/store/resource/version.py
vantage6_algorithm_store-4.13.6.dist-info/METADATA
vantage6_algorithm_store-4.13.6.dist-info/WHEEL
vantage6_algorithm_store-4.13.6.dist-info/top_level.txt
vantage6_algorithm_store-4.13.6.dist-info/RECORD
