Metadata-Version: 2.4
Name: vantage6_algorithm_store
Version: 4.13.6
Summary: Vantage6 algorithm store
Home-page: https://github.com/vantage6/vantage6
Requires-Python: >=3.10
Requires-Dist: flask==3.1.1
Requires-Dist: flask-cors==6.0.0
Requires-Dist: Flask-Principal==0.4.0
Requires-Dist: flask-marshmallow==0.15.0
Requires-Dist: Flask-RESTful==0.3.10
Requires-Dist: gevent==25.4.2
Requires-Dist: jsonschema==4.21.1
Requires-Dist: marshmallow==3.26.2
Requires-Dist: requests==2.32.4
Requires-Dist: schema==0.7.5
Requires-Dist: SQLAlchemy==1.4.46
Requires-Dist: werkzeug==3.1.5
Requires-Dist: vantage6==4.13.6
Requires-Dist: vantage6-common==4.13.6
Provides-Extra: dev
Requires-Dist: coverage==6.4.4; extra == "dev"
Dynamic: description
Dynamic: description-content-type
Dynamic: home-page
Dynamic: provides-extra
Dynamic: requires-dist
Dynamic: requires-python
Dynamic: summary
